<?xml version="1.0" encoding="utf-8" ?><dwsync><file name="check.png" server="ftp.nextstepministries.com//home/andy8383/test.nextstepministries.com/" local="3559143799" remote="3566320676" Dst="-1" /><file name="locked.png" server="ftp.nextstepministries.com//home/andy8383/test.nextstepministries.com/" local="3559144428" remote="3566320676" Dst="-1" /><file name="x.png" server="ftp.nextstepministries.com//home/andy8383/test.nextstepministries.com/" local="3559144134" remote="3566320677" Dst="-1" /><file name=".htaccess" server="ftp.nextstepministries.com//home/andy8383/test.nextstepministries.com/" local="3559203509" remote="3566320675" Dst="-1" /><file name="unlocked.png" server="ftp.nextstepministries.com//home/andy8383/test.nextstepministries.com/" local="3559152639" remote="3566320676" Dst="-1" /><file name="owl-small.png" server="ftp.nextstepministries.com//home/andy8383/test.nextstepministries.com/" local="3566586000" remote="3566586044" Dst="-1" /><file name="GFEFicon80x80.jpg" server="ftp.nextstepministries.com//home/andy8383/test.nextstepministries.com/" local="3561053695" remote="3567520025" Dst="-1" /><file name="hidden.png" server="ftp.nextstepministries.com//home/andy8383/test.nextstepministries.com/" local="3577447773" remote="3577448030" Dst="-1" /><file name="hidden-blue.png" server="ftp.nextstepministries.com//home/andy8383/test.nextstepministries.com/" local="3577457996" remote="3577458076" Dst="-1" /><file name="locked-blue.png" server="ftp.nextstepministries.com//home/andy8383/test.nextstepministries.com/" local="3577457952" remote="3577458076" Dst="-1" /><file name=".DS_Store" server="ftp.nextstepministries.com//home/andy8383/test.nextstepministries.com/" local="3577447826" remote="3577459472" Dst="-1" /></dwsync>